apple/apple.py
applestockprice/applestockprice.py
applestockprice-4.0.0.dist-info/LICENSE
applestockprice-4.0.0.dist-info/METADATA
applestockprice-4.0.0.dist-info/WHEEL
applestockprice-4.0.0.dist-info/top_level.txt
applestockprice-4.0.0.dist-info/RECORD
